traced/__init__.py
traced/backend/database.py
traced/backend/main.py
traced/backend/middleware.py
traced/backend/routers/experiment_router.py
traced/backend/routers/feedback_router.py
traced/backend/routers/prompt_router.py
traced/backend/schemas/eval_schemas.py
traced/cli/__init__.py
traced/cli/commands.py
traced/core/__init__.py
traced/core/complete_async.py
traced/core/config.py
traced/core/context.py
traced/core/logger_model.py
traced/core/rehydrate_experiment.py
traced/core/git/git_fields.py
traced/core/git/gitutil.py
traced/core/utils/serializable_data_class.py
traced/core/utils/serialization.py
traced/frontend/build/.gitkeep
traced/frontend/node_modules/flatted/python/flatted.py
traced/frontend/node_modules/flatted/python/test.py
traced-0.1.5.dist-info/LICENSE
traced-0.1.5.dist-info/METADATA
traced-0.1.5.dist-info/WHEEL
traced-0.1.5.dist-info/entry_points.txt
traced-0.1.5.dist-info/top_level.txt
traced-0.1.5.dist-info/RECORD
